sustech_ncs/NCS_mul_asym.py
sustech_ncs/NCS_mul_pack.py
sustech_ncs/NCS_noMul_pack.py
sustech_ncs/__init__.py
sustech_ncs-0.0.7.dist-info/LICENSE.txt
sustech_ncs-0.0.7.dist-info/METADATA
sustech_ncs-0.0.7.dist-info/WHEEL
sustech_ncs-0.0.7.dist-info/top_level.txt
sustech_ncs-0.0.7.dist-info/RECORD
