Metadata-Version: 2.1
Name: sustech_ncs
Version: 0.0.7
Summary: A python impletation of NCS-C.
Home-page: https://github.com/Joy-Mine/sustech_ncs
Author: Yibo Yang, Jimao Shi
Author-email: 12112222@mail.sustech.edu.cn, 12112218@mail.sustech.edu.cn
Classifier: Programming Language :: Python :: 3
Classifier: License :: OSI Approved :: MIT License
Classifier: Operating System :: OS Independent
License-File: LICENSE.txt
